{
  "id": "Rule_LocationExtraction_P0",
  "fromCuePattern": "(?:在|於|至|屯於|駐於|守於|戰於|會於|攻克|進軍|退守)([\\u4e00-\\u9fff]{1,8}(?:州|郡|縣|城|關|渡|津|寨|山|水|口|原|川|都|京)?)",
  "strongPattern": "([\\u4e00-\\u9fff]{2,8}(?:州|郡|縣|城|關|渡|津|寨|山|水|口|原|川|都|京))",
  "suffixPattern": "(州|郡|縣|城|關|渡|津|寨|山|水|口|原|川|都|京)$",
  "badPrefix": [
    "上",
    "下",
    "入",
    "出",
    "在",
    "守",
    "戰",
    "攻",
    "於",
    "聞",
    "至"
  ],
  "stopTokens": [
    "事件",
    "人物",
    "候選",
    "入城",
    "出城",
    "武將",
    "段落",
    "關係"
  ]
}
